---
layout: post
title:  "Java 同步机制"
date:   2021-06-30 14:59:30
categories: JDK
---

Java中的同步目的在于**协调对临界资源的访问**，保证**多线程环境下共享的、可修改的状态的正确性**。实现同步的方式为加锁，Java中的锁可分为**隐式锁**和**显式锁**两种。隐式锁就是我们最常使用的**synchronized**关键字，
显式锁主要包含两个接口：**Lock和ReadWriteLock**，**显式锁是基于AQS实现**。

#### Synchronized

synchronized关键字是Java中解决并发问题的一种常用、简单的一种方法,其作用有三个：
* 互斥性：确保线程互斥的访问同步代码
* 可见性：保证共享变量的修改能够及时可见
* 有序性：禁止重排序。

synchronized关键字可以修饰方法、以及代码块，synchronized关键字加到**static静态方法和synchronized(class)代码块上都是是给Class类上锁。synchronized关键字加到实例方法上是给对象实例上锁**。
一个线程A调用一个实例对象的非静态synchronized方法，而线程B需要调用这个实例对象所属类的静态synchronized方法，是允许的，不会发生互斥现象，因为访问静态synchronized方法占用的锁是当前类的锁，
而访问非静态synchronized方法占用的锁是当前实例对象锁。具体实现方式如下：

* 修饰代码块.synchronized同步语句块的实现使用的是**monitorenter**和**monitorexit**指令.

```
public void decrAge();                          //synchronized (this){
    descriptor: ()V                             //    age -= 1;
    flags: ACC_PUBLIC                           //}
    Code:
      stack=2, locals=3, args_size=1
         0: aload_0
         1: dup
         2: astore_1
         3: monitorenter                       
         4: getstatic     #2                  // Field age:Ljava/lang/Integer;
         7: invokevirtual #3                  // Method java/lang/Integer.intValue:()I
        10: iconst_1
        11: isub
        12: invokestatic  #4                  // Method java/lang/Integer.valueOf:(I)Ljava/lang/Integer;
        15: putstatic     #2                  // Field age:Ljava/lang/Integer;
        18: aload_1
        19: monitorexit
        20: goto          28
        23: astore_2
        24: aload_1
        25: monitorexit
        26: aload_2
        27: athrow
        28: return

```

* 修饰方法，synchronized方法会被**ACC_SYNCHRONIZED**标识，该标识指明了该方法是一个同步方法，JVM通过该ACC_SYNCHRONIZED访问标志来辨别一个方法是否声明为同步方法。

```
public static synchronized void incrAge();
    descriptor: ()V
    flags: ACC_PUBLIC, ACC_STATIC, ACC_SYNCHRONIZED
    Code:
      stack=2, locals=0, args_size=0
         0: getstatic     #2                  // Field age:Ljava/lang/Integer;
         3: invokevirtual #3                  // Method java/lang/Integer.intValue:()I
         6: iconst_1
         7: iadd
         8: invokestatic  #4                  // Method java/lang/Integer.valueOf:(I)Ljava/lang/Integer;
        11: putstatic     #2                  // Field age:Ljava/lang/Integer;
        14: return
```

每个对象都存在着一个Monitor对象与之关联，synchronized关键字**无论是修饰代码块，还是修饰实例方法和静态方法**，本质上都是**作用于对象的Monitor上**。在HotSpot虚拟机中，**Java对象的存储布局可划分为三部分：对象头、实例数据、
和对齐填充**。对象头包含两部分信息：**MarkWord和实例指针**，MarkWord是有着动态定义的数据结构，当出现锁竞争，即需要**重量级锁时，MarkWord会记录指向Monitor对象的指针**。


##### JVM优化


在HotSpot虚拟机中，Monitor的实现完全是依靠操作系统内部的互斥锁Mutex Lock，涉及到用户态到内核态的切换，所以同步操作是一个无差别的重量级操作。JDK6时，JVM对此进行了改进，提供了三种不同的Monitor实现，也就是常说的三种不同的锁：**偏向锁(Biased Locking)、轻量级锁
和重量级锁**，大大改进了其性能。

* 偏向锁

    当该对象第一次被线程获得锁的时候，发现Mark Word中的thread id为0，表示未偏向任何线程，也叫做匿名偏向(anonymously biased)，则会用CAS指令，将Mark Word中的thread id由0改成当前线程Id。如果成功，则代表获得了偏向锁，
    继续执行同步块中的代码。否则，将偏向锁撤销，升级为轻量级锁。

* 轻量级锁
    
    轻量级锁适用于多个线程交替进入临界区，在整个同步周期内都不存在竞争。具体步骤如下：
    
    * 当线程即将进入同步块时，会在当前线程栈中建立一个每位Lock Record的记录，用户存储对象当前的Mark Word的copy；
    * 使用CAS操作将当前对象的的Mark Word更改为指向当前线程栈内Lock Record的指针；
    * 更新成功，则当前线程获取到该对象的锁，此时对象处于轻量级锁定状态，Mark Word标志位为**00**；
    * 更新失败，检查对象的Mark Word是否指向当前线程的栈帧，如果是就说明当前线程已经拥有了这个对象的锁，那就可以直接进入同步块继续执行，否则说明多个线程竞争锁，进行锁升级。
    

* 重量级锁

    重量级锁的Monitor是基于C++的ObjectMonitor类实现的。ObjectMonitor中有几个关键属性：
                                                                                            
        * _owner：指向持有ObjectMonitor对象的线程
        * _WaitSet：存放处于wait状态的线程队列
        * _EntryList：存放处于等待锁block状态的线程队列
        * _recursions：锁的重入次数
        * _count：用来记录该线程获取锁的次数
        * _cxq
    
    [基本工作机制介绍](https://zhuanlan.zhihu.com/p/356010805)
    

#### AbstractQueuedSynchronizer

Java中的大部分同步类（Lock、Semaphore、ReentrantLock等）都是基于AbstractQueuedSynchronizer(简称为AQS)实现的。AQS是一种提供了原子式管理同步状态、阻塞和唤醒线程功能
以及队列模型的框架。

##### AQS数据结构

AQS的数据结构核心是两个虚拟队列：同步队列sync queue和condition queue。condition queue依赖于内部类ConditionObject实现。

**AQS的同步机制是依靠CLH队列**(Craig、Landin and Hagersten Lock Queue)实现的，**Java中的CLH队列是FIFO的双端双向队列**，实现公平锁。**头节点是一个获取同步状态成功的节点**。线程通过AQS获取锁失败，就会将**线程封装成一个Node节点，插入队列尾**。当有线程释放锁时，
后唤醒头节点的next节点（第二个节点）尝试占用锁。

CLH队列节点实现为AQS的内部类**AbstractQueuedSynchronizer.Node**，数据结构如下：

```
static final class Node {

    static final Node SHARED = new Node();  //用于标识当前节点在等待共享锁
    static final Node EXCLUSIVE = null;  //用于标识当前节点在等待独占锁
    
    static final int CANCELLED =  1;   //当前线程获取锁的请求已取消，不会再参与竞争
    static final int SIGNAL    = -1;   //当前节点释放锁的时候，需要唤醒下一个节点
    static final int CONDITION = -2;   //与Condition相关，当其他线程调用了Condition的signal()方法后，CONDITION状态的结点将从等待队列转移到同步队列中，等待获取同步锁。
    static final int PROPAGATE = -3;   //共享锁时，该状态标识结点的线程处于可运行状态
    
    volatile int waitStatus; //当前节点在队列中的状态，0为初始化，其余状态见上，waitStatus>0 当前节点无效状态，需移除；waitStatus<0 当前节点有效状态。
    
    volatile Node prev;  //前驱结点的引用
    
    volatile Node next;  //后驱节点的引用
    
    volatile Thread thread;  //存储的线程信息
    
    Node nextWaiter;  //Condition相关。AQS中的条件队列 
    
    //Constructor..
}
```

##### 同步状态State

AQS中维护了一个名为state的字段，意为同步状态，是由Volatile修饰的，用于展示当前临界资源的获锁情况。

```
//The synchronization state.
private volatile int state;
```

##### 执行流程

* **获取锁，调用acquire方法，以独占模式获取锁，忽略中断**。tryAcquire返回true，获取锁成功。返回false,获取失败则会通过addWaiter方法追加到CLH队列队尾；

```
public final void acquire(int arg) {
    if (!tryAcquire(arg) &&
        acquireQueued(addWaiter(Node.EXCLUSIVE), arg))
        selfInterrupt();  //未能获取锁，线程中断
}
```

* **加入队列，未获取锁的线程添加到队尾**；

```
private Node addWaiter(Node mode) {
    Node node = new Node(Thread.currentThread(), mode);
    Node pred = tail;                  // 获取原队尾
    if (pred != null) {
        node.prev = pred;
        if (compareAndSetTail(pred, node)) {  ////用cas更新 ,pred是原来队尾，作为预期值，node作为新值
            pred.next = node;
            return node;
        }
    }
    enq(node);  ////前面cas更新失败后，再enq方法中循环用cas更新直到成功
    return node;
}
```

* **出队列时机**，acquireQueued方法中会使线程自旋阻塞，直到获取到锁，节点获取锁的条件为两个：1、前驱节点为头结点；2、前驱节点的waitStatus=Node.SIGNAL；

```
final boolean acquireQueued(final Node node, int arg) {
    boolean failed = true;
    try {
        boolean interrupted = false;
        for (;;) {
            final Node p = node.predecessor();   //获取前驱节点
            if (p == head && tryAcquire(arg)) {  //前驱节点为头结点，再次尝试获取锁
                //获取成功，将当前节点设置为头结点
                setHead(node);   
                p.next = null; // help GC
                failed = false;
                return interrupted;
            }
            // 更改前驱节点的waitStatus=Node.SIGNAL, 如果前驱节点的waitStatus>0(即取消)，则跳过取更前面的节点。
            if (shouldParkAfterFailedAcquire(p, node) &&
                //通过Unsafe.park挂起当前线程，阻塞调用栈
                parkAndCheckInterrupt())
                interrupted = true;
        }
    } finally {
        if (failed)
            cancelAcquire(node);
    }
}
```

* **释放锁**，获取到锁的线程会设置为CLH队列的头部，tryRelease返回true，且head的waitStatus!=0，就会更新head的waitStatus为0并且唤醒线程head.next节点的线程。

```
public final boolean release(int arg) {
    if (tryRelease(arg)) {
        Node h = head;
        if (h != null && h.waitStatus != 0)  
            unparkSuccessor(h);
        return true;
    }
    return false;
}

private void unparkSuccessor(Node node) {
   
    int ws = node.waitStatus;
    if (ws < 0)
        compareAndSetWaitStatus(node, ws, 0);//waitStatus不是取消状态，就设置成0

    Node s = node.next;
    //获取下个waitStatus不为取消的Node
    if (s == null || s.waitStatus > 0) {  
        s = null;
        for (Node t = tail; t != null && t != node; t = t.prev)
            if (t.waitStatus <= 0)
                s = t;
    }
    if (s != null)
        LockSupport.unpark(s.thread);  //唤醒线程
}

```